hough_jax/__init__.py
hough_jax/probabilistic_hough_line.py
hough_jax-0.2.dist-info/METADATA
hough_jax-0.2.dist-info/WHEEL
hough_jax-0.2.dist-info/RECORD
