Metadata-Version: 2.4
Name: hough-jax
Version: 0.2
Summary: JAX implementation of the probabilistic Hough transform for lines
Requires-Python: >=3.12
Requires-Dist: jax>=0.8.1
Requires-Dist: jaxtyping>=0.3.3
Requires-Dist: scikit-image>=0.25.2
Provides-Extra: dev
Requires-Dist: pre-commit>=4.3.0; extra == 'dev'
Requires-Dist: pytest>=8.0.0; extra == 'dev'
Requires-Dist: ruff>=0.12.11; extra == 'dev'
